lcr/__init__.py
lcr_api_2-0.6.3.dist-info/METADATA
lcr_api_2-0.6.3.dist-info/WHEEL
lcr_api_2-0.6.3.dist-info/top_level.txt
lcr_api_2-0.6.3.dist-info/RECORD
