Metadata-Version: 2.4
Name: lcr_api_2
Version: 0.6.3
Summary: An API for the LDS churches Leader and Clerk Resources (LCR),
Home-page: https://github.com/SpencerMKSmith/LCR-API-2
Download-URL: https://github.com/SpencerMKSmith/LCR-API-2/archive/0.6.3.zip
Author: Spencer Smith
Author-email: spencermksmith@gmail.com
License: MIT License
Platform: any
Requires-Dist: requests<3,>=2
Requires-Dist: selenium<5,>=4.0
Requires-Dist: webdriver_manager<4,>=3.0
Dynamic: author
Dynamic: author-email
Dynamic: description
Dynamic: description-content-type
Dynamic: download-url
Dynamic: home-page
Dynamic: license
Dynamic: platform
Dynamic: requires-dist
Dynamic: summary
